myst/__init__.py
myst/client.py
myst/py.typed
myst/settings.py
myst/version.py
myst/adapters/__init__.py
myst/adapters/timing.py
myst/adapters/utils.py
myst/auth/__init__.py
myst/auth/credentials.py
myst/auth/user_credentials_cache.py
myst/connectors/__init__.py
myst/connectors/connector.py
myst/connectors/model_connector.py
myst/connectors/operation_connector.py
myst/connectors/source_connector.py
myst/connectors/model_connectors/__init__.py
myst/connectors/model_connectors/arimax.py
myst/connectors/model_connectors/elastic_net.py
myst/connectors/model_connectors/extra_trees_regression.py
myst/connectors/model_connectors/lightgbm.py
myst/connectors/model_connectors/linear_regression.py
myst/connectors/model_connectors/logistic_regression.py
myst/connectors/model_connectors/mlp_regression.py
myst/connectors/model_connectors/ngboost.py
myst/connectors/model_connectors/random_forest_regression.py
myst/connectors/model_connectors/xgboost.py
myst/connectors/operation_connectors/__init__.py
myst/connectors/operation_connectors/cauchy_distribution.py
myst/connectors/operation_connectors/fill_na.py
myst/connectors/operation_connectors/get_dummies.py
myst/connectors/operation_connectors/laplace_distribution.py
myst/connectors/operation_connectors/lognormal_distribution.py
myst/connectors/operation_connectors/normal_distribution.py
myst/connectors/operation_connectors/numerical_expression.py
myst/connectors/operation_connectors/resampling.py
myst/connectors/operation_connectors/time_transformations.py
myst/connectors/source_connectors/__init__.py
myst/connectors/source_connectors/cleaned_observations.py
myst/connectors/source_connectors/enhanced_forecast.py
myst/connectors/source_connectors/historical_hourly_conditions.py
myst/connectors/source_connectors/holidays.py
myst/connectors/source_connectors/solar_position.py
myst/connectors/source_connectors/time_trends.py
myst/connectors/source_connectors/yes_energy.py
myst/core/__init__.py
myst/core/data/__init__.py
myst_alpha-0.21.1.dist-info/LICENSE
myst_alpha-0.21.1.dist-info/WHEEL
myst_alpha-0.21.1.dist-info/METADATA
myst_alpha-0.21.1.dist-info/RECORD
