Metadata-Version: 2.1
Name: myst-alpha
Version: 0.21.1
Summary: This is the official Python library for the Myst Platform.
Author-email: "Myst AI, Inc." <support@myst.ai>
Requires-Python: >=3.7,<4
Classifier: Development Status :: 3 - Alpha
Classifier: Programming Language :: Python
Classifier: Programming Language :: Python :: 3
Classifier: Programming Language :: Python :: 3.7
Classifier: Programming Language :: Python :: 3.8
Classifier: Programming Language :: Python :: 3.9
Requires-Dist: google-auth <2.0.0,>=1.11.0
Requires-Dist: google-auth-oauthlib <1.0.0,>=0.4.1
Requires-Dist: urllib3 <2.0.0,>=1.24.3
Requires-Dist: toml >=0.10.2,<1
Requires-Dist: httpx >=0.23.0
Requires-Dist: pydantic >=1.8.2,<2
Requires-Dist: numpy >=1.18.0,<1.22; python_version == '3.7'
Requires-Dist: numpy >=1.18.0,<2; python_version >= '3.8'
Requires-Dist: pandas >=1.0,<1.4; python_version == '3.7'
Requires-Dist: pandas >=1.0,<2; python_version >= '3.8'
Requires-Dist: typing-extensions >=3.7.2
Requires-Dist: importlib-metadata
Requires-Dist: coverage >=5.5 ; extra == "test"
Requires-Dist: twine >=1.13.0 ; extra == "test"
Requires-Dist: black >=21.6b0 ; extra == "test"
Requires-Dist: mypy >=0.910,<1 ; extra == "test"
Requires-Dist: types-toml >=0.1.3,<2 ; extra == "test"
Requires-Dist: types-dataclasses >=0.1.5,<2 ; extra == "test"
Requires-Dist: types-setuptools >=57.0.0,<58 ; extra == "test"
Requires-Dist: pytest >=6.2.4,<7 ; extra == "test"
Requires-Dist: pytest-describe >=1.0.0,<2 ; extra == "test"
Requires-Dist: isort >=5.9.1,<6 ; extra == "test"
Requires-Dist: tox >=3.24.0,<4 ; extra == "test"
Requires-Dist: pytest-subtests >=0.5.0,<1 ; extra == "test"
Requires-Dist: pytest-mock >=3.6.1,<4 ; extra == "test"
Requires-Dist: openapi-python-client ==0.11.6 ; extra == "test"
Requires-Dist: typer >=0.3,<1 ; extra == "test"
Requires-Dist: respx >=0.17.1,<1 ; extra == "test"
Requires-Dist: pytest-cov >=2.12.1,<3 ; extra == "test"
Provides-Extra: test
